CHANGELOG.rst
LICENSE
MANIFEST.in
README.rst
setup.py
retdec/__init__.py
retdec/analysis.py
retdec/conn.py
retdec/decompilation.py
retdec/decompiler.py
retdec/exceptions.py
retdec/file.py
retdec/fileinfo.py
retdec/resource.py
retdec/service.py
retdec/test.py
retdec/tools/__init__.py
retdec/tools/decompiler.py
retdec/tools/fileinfo.py
retdec_python.egg-info/PKG-INFO
retdec_python.egg-info/SOURCES.txt
retdec_python.egg-info/dependency_links.txt
retdec_python.egg-info/requires.txt
retdec_python.egg-info/top_level.txt
scripts/decompiler
scripts/fileinfo