Metadata-Version: 1.1
Name: retdec-python
Version: 0.5
Summary: A Python library and tools providing easy access to the retdec.com decompilation service through their public REST API.
Home-page: https://github.com/s3rvac/retdec-python
Author: Petr Zemek
Author-email: s3rvac@gmail.com
License: The MIT License (MIT)
